<annotation>
	<folder>raw</folder>
	<filename>Fisher (32).JPG</filename>
	<path>C:\Users\Agerber\Documents\My Projects\Python - ImageRecognition\object_detection_demo-master\data\raw\Fisher (32).JPG</path>
	<source>
		<database>Unknown</database>
	</source>
	<size>
		<width>143</width>
		<height>184</height>
		<depth>1</depth>
	</size>
	<segmented>0</segmented>
	<object>
		<name>Fisher</name>
		<pose>Unspecified</pose>
		<truncated>1</truncated>
		<difficult>0</difficult>
		<bndbox>
			<xmin>1</xmin>
			<ymin>15</ymin>
			<xmax>142</xmax>
			<ymax>184</ymax>
		</bndbox>
	</object>
</annotation>
